structlog_sentry_lambda/__init__.py
structlog_sentry_lambda/_config.py
structlog_sentry_lambda/structlog_sentry.py
structlog_sentry_lambda-1.4.2.dist-info/LICENSE.txt
structlog_sentry_lambda-1.4.2.dist-info/METADATA
structlog_sentry_lambda-1.4.2.dist-info/WHEEL
structlog_sentry_lambda-1.4.2.dist-info/top_level.txt
structlog_sentry_lambda-1.4.2.dist-info/RECORD
