Metadata-Version: 2.1
Name: structlog-sentry-lambda
Version: 1.4.2
Summary: An AWS approved version of https://github.com/TeoZosa/structlog-sentry-logger which is compatible with AWS Lambda as well as AWS Fargate
Home-page: https://github.com/Rungutan/structlog-sentry-lambda
Author: Rungutan
Author-email: support@rungutan.com
License: UNKNOWN
Download-URL: https://github.com/Rungutan/structlog-sentry-lambda/archive/1.4.2.tar.gz
Project-URL: Bug Reports, https://github.com/Rungutan/structlog-sentry-lambda/issues
Project-URL: Source, https://github.com/Rungutan/structlog-sentry-lambda/
Keywords: rungutan rungutan-cli rungutan_cli cli load testing load-testing load_testing stressstress-testing stress_testing api api-testing api_testing api_load_testing api-load-testingapi_stress_testing api-stress-testing performance performance-testing performance_testingapi-performance-testing api_performance_testing serverless workflow-testing workflow_testingaws sentry aws-sdk aws_sdk awssdk sentry-sdk sentry_sdk sentry sdk structlog logging log loggerlambda fargate ecs console
Platform: UNKNOWN
Classifier: Development Status :: 5 - Production/Stable
Classifier: Intended Audience :: Developers
Classifier: Intended Audience :: Information Technology
Classifier: Intended Audience :: System Administrators
Classifier: Topic :: Software Development :: Testing
Classifier: Topic :: Software Development :: Quality Assurance
Classifier: Topic :: Software Development :: Testing :: Acceptance
Classifier: Topic :: Software Development :: Testing :: BDD
Classifier: Topic :: Software Development :: Testing :: Mocking
Classifier: Topic :: Software Development :: Testing :: Traffic Generation
Classifier: Topic :: Software Development :: Testing :: Unit
Classifier: License :: OSI Approved :: MIT License
Classifier: Programming Language :: Python :: 3.6
Classifier: Programming Language :: Python :: 3.7
Classifier: Programming Language :: Python :: 3.8
Classifier: Programming Language :: Python :: 3.9
Requires-Python: >=3.6
License-File: LICENSE.txt
Requires-Dist: sentry-sdk
Requires-Dist: colorama
Requires-Dist: python-dotenv
Requires-Dist: structlog
Requires-Dist: orjson
Requires-Dist: rich
Provides-Extra: test
Requires-Dist: coverage ; extra == 'test'
